habitrax/__main__.py
habitrax-0.3.6.dist-info/licenses/LICENSE
hbx/__init__.py
hbx/__main__.py
hbx/about.py
hbx/config.py
hbx/debrief.py
hbx/jsonsql.py
hbx/level.py
hbx/logger.py
hbx/main.py
hbx/notebook.py
hbx/profile.py
hbx/setup.py
hbx/slight_edge.py
hbx/soul_work.py
hbx/stat_logic.py
hbx/stats.py
hbx/status_window.py
hbx/storage.py
hbx/tasks.py
hbx/toolbox.py
hbx/data/questions.json
habitrax-0.3.6.dist-info/METADATA
habitrax-0.3.6.dist-info/WHEEL
habitrax-0.3.6.dist-info/entry_points.txt
habitrax-0.3.6.dist-info/top_level.txt
habitrax-0.3.6.dist-info/RECORD
