Metadata-Version: 2.4
Name: Habitrax
Version: 0.3.6
Summary: A terminal-based productivity and life-tracking system.
Author-email: "Caleb M. Sibanda" <darkian.dev@gmail.com>
License: MIT
Project-URL: Homepage, https://github.com/2kDarki/Habitrax
Project-URL: Repository, https://github.com/2kDarki/Habitrax
Project-URL: Issues, https://github.com/2kDarki/Habitrax/issues
Keywords: cli,tracker,productivity,habits,terminal,self-improvement
Classifier: Development Status :: 5 - Production/Stable
Classifier: Environment :: Console
Classifier: Intended Audience :: End Users/Desktop
Classifier: License :: OSI Approved :: MIT License
Classifier: Programming Language :: Python :: 3
Classifier: Programming Language :: Python :: 3.10
Classifier: Operating System :: OS Independent
Classifier: Topic :: Utilities
Requires-Python: >=3.10
License-File: LICENSE
Requires-Dist: tuikit>=0.1.2
Dynamic: license-file
